IM_COOL_BOOY_NGROK/__init__.py
IM_COOL_BOOY_NGROK/__main__.py
IM_COOL_BOOY_NGROK/init.py
IM_COOL_BOOY_NGROK/main.py
IM_COOL_BOOY_NGROK/assets/IMG-20251206-010358.jpg
IM_COOL_BOOY_NGROK/assets/IMG-20251206-010449.jpg
IM_COOL_BOOY_NGROK/assets/IMG-20251206-010530.jpg
IM_COOL_BOOY_NGROK/assets/IMG-20251206-011523-375.jpg
IM_COOL_BOOY_NGROK/assets/IMG_20251206_010811.jpg
im_cool_booy_ngrok-1.1.1.dist-info/licenses/LICENSE
im_cool_booy_ngrok-1.1.1.dist-info/METADATA
im_cool_booy_ngrok-1.1.1.dist-info/WHEEL
im_cool_booy_ngrok-1.1.1.dist-info/entry_points.txt
im_cool_booy_ngrok-1.1.1.dist-info/top_level.txt
im_cool_booy_ngrok-1.1.1.dist-info/RECORD
